snippy_tldr/__init__.py
snippy_tldr/plugin.py
snippy_tldr-0.2.0.dist-info/LICENSE
snippy_tldr-0.2.0.dist-info/METADATA
snippy_tldr-0.2.0.dist-info/WHEEL
snippy_tldr-0.2.0.dist-info/entry_points.txt
snippy_tldr-0.2.0.dist-info/top_level.txt
snippy_tldr-0.2.0.dist-info/RECORD
